cn_clip/__init__.py
cn_clip/clip/__init__.py
cn_clip/clip/bert_tokenizer.py
cn_clip/clip/configuration_bert.py
cn_clip/clip/model.py
cn_clip/clip/modeling_bert.py
cn_clip/clip/utils.py
cn_clip/clip/vocab.txt
cn_clip/clip/model_configs/RBT3-chinese.json
cn_clip/clip/model_configs/RN50.json
cn_clip/clip/model_configs/RoBERTa-wwm-ext-base-chinese.json
cn_clip/clip/model_configs/RoBERTa-wwm-ext-large-chinese.json
cn_clip/clip/model_configs/ViT-B-16.json
cn_clip/clip/model_configs/ViT-B-32.json
cn_clip/clip/model_configs/ViT-H-14.json
cn_clip/clip/model_configs/ViT-L-14-336.json
cn_clip/clip/model_configs/ViT-L-14.json
cn_clip/deploy/__init__.py
cn_clip/deploy/benchmark_utils.py
cn_clip/deploy/onnx_to_tensorrt.py
cn_clip/deploy/pytorch_to_coreml.py
cn_clip/deploy/pytorch_to_onnx.py
cn_clip/deploy/speed_benchmark.py
cn_clip/deploy/tensorrt_utils.py
cn_clip/eval/__init__.py
cn_clip/eval/cvinw_zeroshot_templates.py
cn_clip/eval/data.py
cn_clip/eval/evaluation.py
cn_clip/eval/evaluation_tr.py
cn_clip/eval/extract_features.py
cn_clip/eval/extract_features_onnx.py
cn_clip/eval/extract_features_tensorrt.py
cn_clip/eval/imagenet_zeroshot_templates.py
cn_clip/eval/make_topk_predictions.py
cn_clip/eval/make_topk_predictions_tr.py
cn_clip/eval/transform_ir_annotation_to_tr.py
cn_clip/eval/zeroshot_evaluation.py
cn_clip/preprocess/__init__.py
cn_clip/preprocess/build_lmdb_dataset.py
cn_clip/preprocess/transform_openai_pretrain_weights.py
cn_clip/training/__init__.py
cn_clip/training/data.py
cn_clip/training/logger.py
cn_clip/training/main.py
cn_clip/training/params.py
cn_clip/training/scheduler.py
cn_clip/training/train.py
cn_clip-1.6.0.data/data/clip/vocab.txt
cn_clip-1.6.0.data/data/clip/model_configs/RBT3-chinese.json
cn_clip-1.6.0.data/data/clip/model_configs/RN50.json
cn_clip-1.6.0.data/data/clip/model_configs/RoBERTa-wwm-ext-base-chinese.json
cn_clip-1.6.0.data/data/clip/model_configs/RoBERTa-wwm-ext-large-chinese.json
cn_clip-1.6.0.data/data/clip/model_configs/ViT-B-16.json
cn_clip-1.6.0.dist-info/METADATA
cn_clip-1.6.0.dist-info/WHEEL
cn_clip-1.6.0.dist-info/top_level.txt
cn_clip-1.6.0.dist-info/RECORD
