Metadata-Version: 2.1
Name: cn-clip
Version: 1.6.0
Summary: the Chinese version of CLIP.
Home-page: https://github.com/OFA-Sys/Chinese-CLIP
Author: OFA-Sys
Author-email: 
Keywords: clip
Requires-Dist: numpy
Requires-Dist: tqdm
Requires-Dist: six
Requires-Dist: timm
Requires-Dist: lmdb ==1.3.0
Requires-Dist: torch >=1.7.1
Requires-Dist: torchvision
